{"rate_rps": 136.93, "duration_s": 60.0, "n_requests": 8166, "errors": 0, "mean_ms": 8.29, "p50_ms": 6.25, "p95_ms": 20.32, "p99_ms": 26.57, "std_ms": 5.77, "achieved_rps": 136.1, "active_start_ts": 1778694749.833, "active_end_ts": 1778694809.82, "run_type": "lambda_sweep", "lambda_frac": 0.25, "target_rps": 136.93, "run_idx": 3, "l_max_ms": 100.0, "timestamp": "2026-05-14T02:53:29+0900", "device": "gpu-server", "model": "mobilenet-v2-100", "policy": "full_dvfs", "dvfs_mode": 7, "dvfs_mode_label": "1545MHz", "condition_tag": "dvfs7", "run_family": "full_dvfs", "operating_condition": {"kind": "dvfs_mode", "condition_tag": "dvfs7", "legacy_policy": "full_dvfs", "dvfs_mode": 7, "dvfs_mode_label": "1545MHz", "expected_ep": "CUDAExecutionProvider", "expected_nvpmodel": null, "expected_gpu_freq_mhz": 1545}, "schema_version": 4, "deploy_provenance": {"infer_server_sha256": "8eddb3f76c41145b", "model_filename": "mobilenet-v2-100.onnx", "model_sha256": "be410f972ea40c39", "ort_version": "1.16.3"}, "confirmation": {"rounds": [{"round": 1, "pass": true, "runs": [{"active_start_ts": 1778694749.833, "active_end_ts": 1778694809.82}]}]}, "power_trace": {"schema_version": 1, "source": "direct_shelly", "shelly_hostname": "gpu-server", "poll_interval_s": 0.5, "trace_start_ts": 1778694736.4122915, "total_sample_count": 141, "collector_errors": 0, "warm_idle": {"start_ts": 1778694736.4122915, "end_ts": 1778694744.6446831, "duration_s": 8.2, "avg_watts": 106.19, "median_watts": 106.2, "std_watts": 2.187, "sample_count": 16}, "passing_round": 1, "confirmation_runs": [{"run_index": 0, "active_start_ts": 1778694749.833, "active_end_ts": 1778694809.82, "duration_s": 60.0, "avg_watts": 115.59, "sample_count": 114, "delta_watts": 9.39}], "summary": {"warm_idle_median_watts": 106.2, "serving_median_watts": 115.59, "delta_median_watts": 9.39, "n_valid_runs": 1}, "raw_samples": [{"ts": 1778694736.412, "watts": 104.4}, {"ts": 1778694736.94, "watts": 104.7}, {"ts": 1778694737.468, "watts": 104.7}, {"ts": 1778694737.997, "watts": 108.1}, {"ts": 1778694738.522, "watts": 104.6}, {"ts": 1778694739.054, "watts": 104.6}, {"ts": 1778694739.585, "watts": 103.8}, {"ts": 1778694740.115, "watts": 103.8}, {"ts": 1778694740.641, "watts": 111.1}, {"ts": 1778694741.171, "watts": 111.1}, {"ts": 1778694741.695, "watts": 106.2}, {"ts": 1778694742.229, "watts": 106.2}, {"ts": 1778694742.76, "watts": 106.2}, {"ts": 1778694743.29, "watts": 106.2}, {"ts": 1778694743.815, "watts": 106.7}, {"ts": 1778694744.34, "watts": 106.7}, {"ts": 1778694744.869, "watts": 106.0}, {"ts": 1778694745.392, "watts": 106.0}, {"ts": 1778694745.922, "watts": 106.5}, {"ts": 1778694746.447, "watts": 106.5}, {"ts": 1778694746.975, "watts": 116.0}, {"ts": 1778694747.501, "watts": 116.0}, {"ts": 1778694748.031, "watts": 114.0}, {"ts": 1778694748.555, "watts": 114.2}, {"ts": 1778694749.087, "watts": 114.2}, {"ts": 1778694749.621, "watts": 113.7}, {"ts": 1778694750.148, "watts": 113.7}, {"ts": 1778694750.676, "watts": 112.7}, {"ts": 1778694751.201, "watts": 112.7}, {"ts": 1778694751.73, "watts": 114.5}, {"ts": 1778694752.263, "watts": 114.5}, {"ts": 1778694752.795, "watts": 114.5}, {"ts": 1778694753.322, "watts": 114.5}, {"ts": 1778694753.849, "watts": 114.5}, {"ts": 1778694754.372, "watts": 114.5}, {"ts": 1778694754.899, "watts": 116.0}, {"ts": 1778694755.426, "watts": 116.0}, {"ts": 1778694755.95, "watts": 114.0}, {"ts": 1778694756.482, "watts": 114.0}, {"ts": 1778694757.011, "watts": 114.0}, {"ts": 1778694757.538, "watts": 118.6}, {"ts": 1778694758.061, "watts": 118.6}, {"ts": 1778694758.584, "watts": 114.6}, {"ts": 1778694759.107, "watts": 114.6}, {"ts": 1778694759.636, "watts": 117.5}, {"ts": 1778694760.168, "watts": 117.5}, {"ts": 1778694760.698, "watts": 115.6}, {"ts": 1778694761.222, "watts": 115.6}, {"ts": 1778694761.747, "watts": 116.8}, {"ts": 1778694762.276, "watts": 116.8}, {"ts": 1778694762.801, "watts": 113.6}, {"ts": 1778694763.328, "watts": 113.6}, {"ts": 1778694763.86, "watts": 116.5}, {"ts": 1778694764.39, "watts": 116.5}, {"ts": 1778694764.913, "watts": 116.5}, {"ts": 1778694765.437, "watts": 116.5}, {"ts": 1778694765.962, "watts": 114.0}, {"ts": 1778694766.491, "watts": 114.0}, {"ts": 1778694767.018, "watts": 116.4}, {"ts": 1778694767.546, "watts": 116.7}, {"ts": 1778694768.072, "watts": 116.7}, {"ts": 1778694768.598, "watts": 112.3}, {"ts": 1778694769.121, "watts": 112.3}, {"ts": 1778694769.643, "watts": 112.9}, {"ts": 1778694770.167, "watts": 112.9}, {"ts": 1778694770.694, "watts": 113.0}, {"ts": 1778694771.225, "watts": 113.0}, {"ts": 1778694771.753, "watts": 114.6}, {"ts": 1778694772.277, "watts": 114.6}, {"ts": 1778694772.801, "watts": 116.0}, {"ts": 1778694773.324, "watts": 116.0}, {"ts": 1778694773.851, "watts": 115.5}, {"ts": 1778694774.38, "watts": 115.5}, {"ts": 1778694774.912, "watts": 118.4}, {"ts": 1778694775.442, "watts": 118.4}, {"ts": 1778694775.969, "watts": 115.3}, {"ts": 1778694776.499, "watts": 115.3}, {"ts": 1778694777.025, "watts": 116.9}, {"ts": 1778694777.555, "watts": 118.3}, {"ts": 1778694778.086, "watts": 118.3}, {"ts": 1778694778.615, "watts": 112.0}, {"ts": 1778694779.138, "watts": 112.0}, {"ts": 1778694779.664, "watts": 113.5}, {"ts": 1778694780.188, "watts": 113.5}, {"ts": 1778694780.719, "watts": 123.0}, {"ts": 1778694781.245, "watts": 123.0}, {"ts": 1778694781.772, "watts": 114.4}, {"ts": 1778694782.301, "watts": 114.4}, {"ts": 1778694782.831, "watts": 116.9}, {"ts": 1778694783.36, "watts": 116.9}, {"ts": 1778694783.887, "watts": 116.6}, {"ts": 1778694784.415, "watts": 116.6}, {"ts": 1778694784.946, "watts": 116.9}, {"ts": 1778694785.477, "watts": 116.9}, {"ts": 1778694786.002, "watts": 115.1}, {"ts": 1778694786.573, "watts": 115.9}, {"ts": 1778694787.101, "watts": 115.9}, {"ts": 1778694787.627, "watts": 117.2}, {"ts": 1778694788.153, "watts": 117.2}, {"ts": 1778694788.677, "watts": 116.2}, {"ts": 1778694789.202, "watts": 116.2}, {"ts": 1778694789.725, "watts": 112.9}, {"ts": 1778694790.251, "watts": 112.9}, {"ts": 1778694790.775, "watts": 111.6}, {"ts": 1778694791.301, "watts": 111.6}, {"ts": 1778694791.826, "watts": 113.0}, {"ts": 1778694792.352, "watts": 113.0}, {"ts": 1778694792.876, "watts": 114.4}, {"ts": 1778694793.407, "watts": 114.4}, {"ts": 1778694793.939, "watts": 115.9}, {"ts": 1778694794.469, "watts": 115.9}, {"ts": 1778694794.998, "watts": 117.5}, {"ts": 1778694795.524, "watts": 115.2}, {"ts": 1778694796.048, "watts": 115.2}, {"ts": 1778694796.579, "watts": 114.7}, {"ts": 1778694797.113, "watts": 114.7}, {"ts": 1778694797.645, "watts": 120.2}, {"ts": 1778694798.173, "watts": 120.2}, {"ts": 1778694798.703, "watts": 114.8}, {"ts": 1778694799.233, "watts": 114.8}, {"ts": 1778694799.756, "watts": 113.4}, {"ts": 1778694800.279, "watts": 113.4}, {"ts": 1778694800.807, "watts": 121.1}, {"ts": 1778694801.336, "watts": 121.1}, {"ts": 1778694801.864, "watts": 117.1}, {"ts": 1778694802.39, "watts": 117.1}, {"ts": 1778694802.916, "watts": 114.1}, {"ts": 1778694803.44, "watts": 114.1}, {"ts": 1778694803.963, "watts": 116.9}, {"ts": 1778694804.489, "watts": 116.9}, {"ts": 1778694805.017, "watts": 122.6}, {"ts": 1778694805.545, "watts": 114.5}, {"ts": 1778694806.069, "watts": 114.5}, {"ts": 1778694806.594, "watts": 118.0}, {"ts": 1778694807.12, "watts": 118.0}, {"ts": 1778694807.646, "watts": 117.0}, {"ts": 1778694808.172, "watts": 117.0}, {"ts": 1778694808.704, "watts": 113.4}, {"ts": 1778694809.235, "watts": 113.4}, {"ts": 1778694809.762, "watts": 113.0}, {"ts": 1778694810.291, "watts": 113.0}], "status": "ok"}}