{"rate_rps": 164.55, "duration_s": 60.0, "n_requests": 9853, "errors": 0, "mean_ms": 12.75, "p50_ms": 11.19, "p95_ms": 23.95, "p99_ms": 32.9, "std_ms": 5.95, "achieved_rps": 164.22, "active_start_ts": 1778680594.29, "active_end_ts": 1778680654.298, "run_type": "lambda_sweep", "lambda_frac": 0.75, "target_rps": 164.55, "run_idx": 6, "l_max_ms": 100.0, "timestamp": "2026-05-13T22:57:34+0900", "device": "xavier", "model": "mobilenet-v2-100", "policy": "full_dvfs", "dvfs_mode": 2, "dvfs_mode_label": "MODE_15W_6CORE", "condition_tag": "dvfs2", "run_family": "full_dvfs", "operating_condition": {"kind": "dvfs_mode", "condition_tag": "dvfs2", "legacy_policy": "full_dvfs", "dvfs_mode": 2, "dvfs_mode_label": "MODE_15W_6CORE", "expected_ep": "TensorrtExecutionProvider", "expected_nvpmodel": "MODE_15W_6CORE", "expected_gpu_freq_mhz": null}, "schema_version": 4, "deploy_provenance": {"infer_server_sha256": "8eddb3f76c41145b", "model_filename": "mobilenet-v2-100.onnx", "model_sha256": "be410f972ea40c39", "ort_version": "1.16.0"}, "confirmation": {"rounds": [{"round": 1, "pass": true, "runs": [{"active_start_ts": 1778680594.29, "active_end_ts": 1778680654.298}]}]}, "power_trace": {"schema_version": 1, "source": "direct_shelly", "shelly_hostname": "jetson-xavier", "poll_interval_s": 0.5, "trace_start_ts": 1778680580.8662863, "total_sample_count": 142, "collector_errors": 0, "warm_idle": {"start_ts": 1778680580.8662863, "end_ts": 1778680589.092681, "duration_s": 8.2, "avg_watts": 9.92, "median_watts": 9.9, "std_watts": 0.118, "sample_count": 16}, "passing_round": 1, "confirmation_runs": [{"run_index": 0, "active_start_ts": 1778680594.29, "active_end_ts": 1778680654.298, "duration_s": 60.0, "avg_watts": 16.41, "sample_count": 113, "delta_watts": 6.51}], "summary": {"warm_idle_median_watts": 9.9, "serving_median_watts": 16.41, "delta_median_watts": 6.51, "n_valid_runs": 1}, "raw_samples": [{"ts": 1778680580.866, "watts": 10.1}, {"ts": 1778680581.395, "watts": 10.1}, {"ts": 1778680581.921, "watts": 10.0}, {"ts": 1778680582.446, "watts": 10.0}, {"ts": 1778680582.977, "watts": 9.8}, {"ts": 1778680583.505, "watts": 9.8}, {"ts": 1778680584.04, "watts": 9.9}, {"ts": 1778680584.57, "watts": 9.9}, {"ts": 1778680585.096, "watts": 9.8}, {"ts": 1778680585.623, "watts": 9.8}, {"ts": 1778680586.154, "watts": 9.8}, {"ts": 1778680586.683, "watts": 9.8}, {"ts": 1778680587.214, "watts": 10.0}, {"ts": 1778680587.745, "watts": 10.0}, {"ts": 1778680588.28, "watts": 9.8}, {"ts": 1778680588.808, "watts": 10.1}, {"ts": 1778680589.337, "watts": 10.1}, {"ts": 1778680589.873, "watts": 11.0}, {"ts": 1778680590.401, "watts": 11.0}, {"ts": 1778680590.929, "watts": 15.4}, {"ts": 1778680591.457, "watts": 15.4}, {"ts": 1778680591.984, "watts": 16.3}, {"ts": 1778680592.513, "watts": 16.3}, {"ts": 1778680593.042, "watts": 16.7}, {"ts": 1778680593.569, "watts": 16.7}, {"ts": 1778680594.097, "watts": 16.2}, {"ts": 1778680594.63, "watts": 16.2}, {"ts": 1778680595.158, "watts": 16.6}, {"ts": 1778680595.686, "watts": 16.6}, {"ts": 1778680596.215, "watts": 16.8}, {"ts": 1778680596.742, "watts": 16.8}, {"ts": 1778680597.268, "watts": 16.1}, {"ts": 1778680597.805, "watts": 16.6}, {"ts": 1778680598.333, "watts": 16.6}, {"ts": 1778680598.859, "watts": 16.4}, {"ts": 1778680599.386, "watts": 16.4}, {"ts": 1778680599.913, "watts": 16.7}, {"ts": 1778680600.442, "watts": 16.7}, {"ts": 1778680600.981, "watts": 15.4}, {"ts": 1778680601.512, "watts": 15.4}, {"ts": 1778680602.043, "watts": 16.0}, {"ts": 1778680602.576, "watts": 16.0}, {"ts": 1778680603.106, "watts": 16.3}, {"ts": 1778680603.641, "watts": 16.3}, {"ts": 1778680604.173, "watts": 15.9}, {"ts": 1778680604.702, "watts": 15.9}, {"ts": 1778680605.233, "watts": 16.0}, {"ts": 1778680605.761, "watts": 16.0}, {"ts": 1778680606.289, "watts": 15.6}, {"ts": 1778680606.818, "watts": 17.0}, {"ts": 1778680607.344, "watts": 17.0}, {"ts": 1778680607.871, "watts": 16.4}, {"ts": 1778680608.396, "watts": 16.4}, {"ts": 1778680608.923, "watts": 16.2}, {"ts": 1778680609.454, "watts": 16.2}, {"ts": 1778680609.983, "watts": 16.6}, {"ts": 1778680610.518, "watts": 16.6}, {"ts": 1778680611.045, "watts": 16.9}, {"ts": 1778680611.572, "watts": 16.9}, {"ts": 1778680612.099, "watts": 16.1}, {"ts": 1778680612.627, "watts": 16.1}, {"ts": 1778680613.165, "watts": 15.7}, {"ts": 1778680613.692, "watts": 15.7}, {"ts": 1778680614.22, "watts": 16.8}, {"ts": 1778680614.746, "watts": 16.8}, {"ts": 1778680615.274, "watts": 16.7}, {"ts": 1778680615.826, "watts": 16.1}, {"ts": 1778680616.354, "watts": 16.1}, {"ts": 1778680616.881, "watts": 17.0}, {"ts": 1778680617.407, "watts": 17.0}, {"ts": 1778680617.938, "watts": 16.7}, {"ts": 1778680618.465, "watts": 16.7}, {"ts": 1778680619.001, "watts": 17.0}, {"ts": 1778680619.53, "watts": 17.0}, {"ts": 1778680620.057, "watts": 16.8}, {"ts": 1778680620.583, "watts": 16.8}, {"ts": 1778680621.111, "watts": 16.1}, {"ts": 1778680621.638, "watts": 16.1}, {"ts": 1778680622.177, "watts": 16.8}, {"ts": 1778680622.705, "watts": 16.8}, {"ts": 1778680623.236, "watts": 16.6}, {"ts": 1778680623.773, "watts": 16.4}, {"ts": 1778680624.301, "watts": 16.4}, {"ts": 1778680624.839, "watts": 16.3}, {"ts": 1778680625.367, "watts": 16.3}, {"ts": 1778680625.899, "watts": 16.0}, {"ts": 1778680626.427, "watts": 16.0}, {"ts": 1778680626.954, "watts": 16.5}, {"ts": 1778680627.48, "watts": 16.5}, {"ts": 1778680628.012, "watts": 17.3}, {"ts": 1778680628.542, "watts": 17.3}, {"ts": 1778680629.067, "watts": 16.3}, {"ts": 1778680629.61, "watts": 16.3}, {"ts": 1778680630.137, "watts": 15.7}, {"ts": 1778680630.666, "watts": 15.7}, {"ts": 1778680631.204, "watts": 17.2}, {"ts": 1778680631.737, "watts": 17.2}, {"ts": 1778680632.272, "watts": 16.8}, {"ts": 1778680632.802, "watts": 16.4}, {"ts": 1778680633.336, "watts": 16.4}, {"ts": 1778680633.865, "watts": 15.8}, {"ts": 1778680634.393, "watts": 15.8}, {"ts": 1778680634.933, "watts": 16.1}, {"ts": 1778680635.461, "watts": 16.1}, {"ts": 1778680635.989, "watts": 16.1}, {"ts": 1778680636.515, "watts": 16.1}, {"ts": 1778680637.044, "watts": 16.2}, {"ts": 1778680637.57, "watts": 16.2}, {"ts": 1778680638.101, "watts": 16.7}, {"ts": 1778680638.627, "watts": 16.7}, {"ts": 1778680639.153, "watts": 17.1}, {"ts": 1778680639.686, "watts": 17.1}, {"ts": 1778680640.213, "watts": 16.3}, {"ts": 1778680640.74, "watts": 16.3}, {"ts": 1778680641.27, "watts": 16.2}, {"ts": 1778680641.799, "watts": 15.6}, {"ts": 1778680642.327, "watts": 15.6}, {"ts": 1778680642.86, "watts": 17.1}, {"ts": 1778680643.388, "watts": 17.1}, {"ts": 1778680643.918, "watts": 16.0}, {"ts": 1778680644.447, "watts": 16.0}, {"ts": 1778680644.976, "watts": 17.2}, {"ts": 1778680645.508, "watts": 17.2}, {"ts": 1778680646.038, "watts": 17.2}, {"ts": 1778680646.566, "watts": 17.2}, {"ts": 1778680647.1, "watts": 17.0}, {"ts": 1778680647.63, "watts": 17.0}, {"ts": 1778680648.159, "watts": 16.5}, {"ts": 1778680648.697, "watts": 16.5}, {"ts": 1778680649.222, "watts": 15.9}, {"ts": 1778680649.753, "watts": 15.9}, {"ts": 1778680650.294, "watts": 16.3}, {"ts": 1778680650.824, "watts": 17.4}, {"ts": 1778680651.357, "watts": 17.4}, {"ts": 1778680651.888, "watts": 15.8}, {"ts": 1778680652.417, "watts": 15.8}, {"ts": 1778680652.943, "watts": 14.7}, {"ts": 1778680653.476, "watts": 14.7}, {"ts": 1778680654.004, "watts": 16.3}, {"ts": 1778680654.55, "watts": 16.3}, {"ts": 1778680655.081, "watts": 16.3}, {"ts": 1778680655.612, "watts": 16.3}], "status": "ok"}}